libjth/__init__.py
libjth/enums.py
libjth-0.3.0.dist-info/METADATA
libjth-0.3.0.dist-info/WHEEL
libjth-0.3.0.dist-info/licenses/LICENSE.md
libjth-0.3.0.dist-info/RECORD
